ttt/__init__.py
ttt/__main__.py
ttt/chunker.py
ttt/config.py
ttt/models.py
turbo_text_transformer-0.1.6.dist-info/METADATA
turbo_text_transformer-0.1.6.dist-info/LICENSE
turbo_text_transformer-0.1.6.dist-info/WHEEL
turbo_text_transformer-0.1.6.dist-info/entry_points.txt
turbo_text_transformer-0.1.6.dist-info/RECORD
