Metadata-Version: 2.1
Name: turbo-text-transformer
Version: 0.1.6
Summary: 
Home-page: https://github.com/fergusfettes/turbo-text-transformer
Author: fergus
Author-email: fergusfettes@gmail.com
Requires-Python: >3.8
Classifier: Programming Language :: Python :: 3
Classifier: Programming Language :: Python :: 3.9
Classifier: Programming Language :: Python :: 3.10
Classifier: Programming Language :: Python :: 3.11
Requires-Dist: click (>=8.1.3,<9.0.0)
Requires-Dist: colored (>=1.4.4,<2.0.0)
Requires-Dist: openai (>=0.27.0,<0.28.0)
Requires-Dist: pyyaml (>=6.0,<7.0)
Requires-Dist: tiktoken (>=0.2.0,<0.3.0)
Requires-Dist: turbo-text-transformer-prompts (>=0.1.8,<0.2.0)
